{
  "meatParcel": {
    "names": ["Beef","Chicken","Fowl"],
    "logisticTypes": ["mealSupplies"],
    "slots": [64],
    "cargoType": "parcel",
    "rarity": 1,
    "worth": 2.3,
    "generationChance": 0.3,
    "duplicationChance": [1,0.5,0.25],
    "offerDuration": 360,
    "weight": [25,50,75],
    "modChance": {"post": 0.10}
  },
  "breadParcel": {
    "names": ["Baked Goods"],
    "logisticTypes": ["mealSupplies"],
    "slots": [64],
    "cargoType": "parcel",
    "rarity": 1,
    "worth": 2.2,
    "generationChance": 0.3,
    "duplicationChance": [1,0.5],
    "offerDuration": 360,
    "weight": [100,150,200],
    "modChance": {"post": 0.10}
  },
  "defectiveReturns": {
    "names": ["Returns"],
    "logisticTypes": ["defectiveReturns"],
    "slots": [16,32,64],
    "cargoType": "parcel",
    "rarity": 1,
    "worth": 2,
    "generationChance": 0.3,
    "duplicationChance": [1,0.5,0.25],
    "offerDuration": 360,
    "weight": [10,25,40],
    "modChance": {}
  },
  "sideDishParcel": {
    "names": ["Cheese","Fruit","Vegetables","Misc. Ingredients"],
    "logisticTypes": ["sideDishSupplies"],
    "slots": [16,32],
    "cargoType": "parcel",
    "rarity": 1,
    "worth": 2,
    "generationChance": 0.3,
    "duplicationChance": [1,1,0.5,0.25],
    "offerDuration": 360,
    "weight": [10,25,40],
    "modChance": {"precious": 0.5}
  },
  "spiritsParcel": {
    "names": ["Wine","Liquor","beer"],
    "logisticTypes": ["spiritsSupplies"],
    "slots": [32,64],
    "cargoType": "parcel",
    "rarity": 1,
    "worth": 3,
    "generationChance": 0.3,
    "duplicationChance": [0.5,1,0.25],
    "offerDuration": 360,
    "weight": [80,100,130],
    "modChance": {"precious": 0.2}
  },
  "drinkParcel": {
    "names": ["Tasti-Cola"],
    "logisticTypes": ["drinkSupplies"],
    "slots": [64,128],
    "cargoType": "parcel",
    "rarity": 1,
    "worth": 2,
    "generationChance": 0.3,
    "duplicationChance": [0.75,1,1,0.5],
    "offerDuration": 360,
    "weight": [100,150,250],
    "modChance": {"precious": 3}
  },
  "seafoodParcel": {
	"names": ["lobster","cod","salmon","seabass","halibut"],
	"logisticTypes": ["seafoodSupplies"],
	"slots": [8,16],
    "cargoType": "parcel",
    "rarity": 1,
    "worth": 4,
    "generationChance": 1,
    "duplicationChance": [1,1,0.5,0.25],
    "offerDuration": 120,
    "weight": [150],
    "modChance": {"supplies": 3}
  },
  "smallTakeoutOrder": {
    "names":["Food Order","Group Food Order","Food Menu"],
    "logisticTypes":["takeout"],
    "slots":[1,2,3],
    "cargoType":"parcel",
    "rarity":1,
    "worth":6,
    "generationChance":2,
    "duplicationChance":[1,0.5],
    "offerDuration":120,
    "weight":[10,20,30],
    "modChance":{"timed":0.75},
  },
  "largeTakeoutOrder": {
    "names":["Food Banquet", "Party Platter", "Company Food Order"],
    "logisticTypes":["takeout"],
    "slots":[3,4,5,6],
    "cargoType":"parcel",
    "rarity":1,
    "worth":5,
    "generationChance":0.2,
    "duplicationChance":[1],
    "offerDuration":120,
    "weight":[40],
    "modChance":{"timed":0.75},
  },
  "diningUtensils": {
    "names":["Glasses","Stemware","Cutlery","Plates"],
    "logisticTypes":["prepSupplies"],
    "slots":[6,8],
    "cargoType":"parcel",
    "rarity":2,
    "worth":4,
    "generationChance":0.4,
    "duplicationChance":[1,0.5],
    "offerDuration":300,
    "weight":[5],
    "modChance":{"supplies":1},
  },
  "cookingUtensils": {
    "names":["Grill Cleaner","Cooking Cutlery","Kitchen Utensils","Cutting Board"],
    "logisticTypes":["prepSupplies"],
    "slots":[9,12,24],
    "cargoType":"parcel",
    "rarity":2,
    "worth":2,
    "generationChance":0.4,
    "duplicationChance":[1,0.5],
    "offerDuration":300,
    "weight":[30],
    "modChance":{"supplies":1},
  },
  "restaurantAppliances": {
    "names":["Oven","Soda Machine","Industrial Fryer"],
    "logisticTypes":["prepSupplies"],
    "slots":[128,],
    "cargoType":"parcel",
    "rarity":4,
    "worth":5,
    "generationChance":0.2,
    "offerDuration":300,
    "weight":[350],
    "modChance":{"large":1},
  },
  "diningFurniture": {
    "names":[,"Furniture Set"],
    "logisticTypes":["prepSupplies"],
    "slots":64,
    "cargoType":"parcel",
    "rarity":4,
    "worth":4.2,
    "generationChance":0.2,
    "offerDuration":300,
    "weight":[200],
    "modChance":{"large":1},
  },
  "secretIngredients": {
    "names":["Secret Ingredients"],
    "logisticTypes":["prepSupplies"],
    "slots":40,
    "cargoType":"parcel",
    "rarity":4,
    "worth":10,
    "generationChance":0.05,
    "offerDuration":300,
    "weight":[5],
  },  
}